discord_self/__init__.py
discord_self/__main__.py
discord_self/abc.py
discord_self/activity.py
discord_self/affinity.py
discord_self/application.py
discord_self/asset.py
discord_self/audit_logs.py
discord_self/automod.py
discord_self/backoff.py
discord_self/billing.py
discord_self/calls.py
discord_self/channel.py
discord_self/client.py
discord_self/collectible.py
discord_self/colour.py
discord_self/commands.py
discord_self/components.py
discord_self/connections.py
discord_self/context_managers.py
discord_self/directory.py
discord_self/embeds.py
discord_self/emoji.py
discord_self/entitlements.py
discord_self/enums.py
discord_self/errors.py
discord_self/experiment.py
discord_self/file.py
discord_self/flags.py
discord_self/gateway.py
discord_self/guild.py
discord_self/guild_premium.py
discord_self/http.py
discord_self/integrations.py
discord_self/interactions.py
discord_self/invite.py
discord_self/library.py
discord_self/member.py
discord_self/mentions.py
discord_self/message.py
discord_self/metadata.py
discord_self/mixins.py
discord_self/modal.py
discord_self/oauth2.py
discord_self/object.py
discord_self/oggparse.py
discord_self/onboarding.py
discord_self/opus.py
discord_self/partial_emoji.py
discord_self/payments.py
discord_self/permissions.py
discord_self/player.py
discord_self/poll.py
discord_self/primary_guild.py
discord_self/profile.py
discord_self/promotions.py
discord_self/raw_models.py
discord_self/reaction.py
discord_self/read_state.py
discord_self/relationship.py
discord_self/role.py
discord_self/scheduled_event.py
discord_self/settings.py
discord_self/stage_instance.py
discord_self/state.py
discord_self/sticker.py
discord_self/store.py
discord_self/subscriptions.py
discord_self/team.py
discord_self/template.py
discord_self/threads.py
discord_self/tracking.py
discord_self/tutorial.py
discord_self/user.py
discord_self/utils.py
discord_self/voice_client.py
discord_self/voice_state.py
discord_self/welcome_screen.py
discord_self/widget.py
discord_self-2.1.0.dist-info/licenses/LICENSE
discord_self-2.1.0.dist-info/METADATA
discord_self-2.1.0.dist-info/WHEEL
discord_self-2.1.0.dist-info/top_level.txt
discord_self-2.1.0.dist-info/RECORD
