Metadata-Version: 2.4
Name: discord_self
Version: 2.1.0
Summary: A Python wrapper for the Discord user API
Home-page: https://github.com/svaningelgem/discord_self
Author: Steven Van Ingelgem
Author-email: steven@vaningelgem.be
License: The MIT License (MIT)
Project-URL: Documentation, https://discordpy-self.readthedocs.io/en/latest/
Project-URL: Issue tracker, https://github.com/dolfies/discord.py-self/issues
Project-URL: Project updates, https://t.me/dpy_self
Project-URL: Discussion & support, https://t.me/dpy_self_discussions
Classifier: Development Status :: 5 - Production/Stable
Classifier: Intended Audience :: Developers
Classifier: Natural Language :: English
Classifier: Operating System :: OS Independent
Classifier: Programming Language :: Python :: 3.10
Classifier: Programming Language :: Python :: 3.11
Classifier: Programming Language :: Python :: 3.12
Classifier: Programming Language :: Python :: 3.13
Classifier: Programming Language :: Python :: 3.14
Classifier: Topic :: Internet
Classifier: Topic :: Software Development :: Libraries
Classifier: Topic :: Software Development :: Libraries :: Python Modules
Classifier: Topic :: Utilities
Classifier: Typing :: Typed
Requires-Python: >=3.10
License-File: LICENSE
Requires-Dist: aiohttp<4,>=3.7.4
Requires-Dist: curl_cffi<1,>=0.14.0
Requires-Dist: tzlocal<6,>=4.0.0
Requires-Dist: discord_protos<1.0.0
Requires-Dist: audioop-lts; python_version >= "3.13"
Provides-Extra: voice
Requires-Dist: PyNaCl<1.6,>=1.5.0; extra == "voice"
Requires-Dist: davey==0.1.0; extra == "voice"
Provides-Extra: docs
Requires-Dist: sphinx==4.4.0; extra == "docs"
Requires-Dist: sphinxcontrib_trio==1.1.2; extra == "docs"
Requires-Dist: sphinxcontrib-websupport==1.2.4; extra == "docs"
Requires-Dist: sphinxcontrib-applehelp==1.0.4; extra == "docs"
Requires-Dist: sphinxcontrib-devhelp==1.0.2; extra == "docs"
Requires-Dist: sphinxcontrib-htmlhelp==2.0.1; extra == "docs"
Requires-Dist: sphinxcontrib-jsmath==1.0.1; extra == "docs"
Requires-Dist: sphinxcontrib-qthelp==1.0.3; extra == "docs"
Requires-Dist: sphinxcontrib-serializinghtml==1.1.5; extra == "docs"
Requires-Dist: typing-extensions<5,>=4.3; extra == "docs"
Requires-Dist: sphinx-inline-tabs==2023.4.21; extra == "docs"
Requires-Dist: imghdr-lts==1.0.0; python_version >= "3.13" and extra == "docs"
Provides-Extra: speed
Requires-Dist: orjson>=3.5.4; extra == "speed"
Requires-Dist: aiodns>=1.1; sys_platform != "win32" and extra == "speed"
Requires-Dist: Brotli; extra == "speed"
Requires-Dist: cchardet==2.1.7; python_version < "3.10" and extra == "speed"
Requires-Dist: mmh3>=2.5; extra == "speed"
Requires-Dist: zstandard>=0.23.0; python_version <= "3.13" and extra == "speed"
Provides-Extra: test
Requires-Dist: coverage[toml]; extra == "test"
Requires-Dist: pytest; extra == "test"
Requires-Dist: pytest-asyncio; extra == "test"
Requires-Dist: pytest-cov; extra == "test"
Requires-Dist: pytest-mock; extra == "test"
Requires-Dist: typing-extensions<5,>=4.3; extra == "test"
Requires-Dist: tzdata; sys_platform == "win32" and extra == "test"
Provides-Extra: dev
Requires-Dist: ruff==0.12; extra == "dev"
Requires-Dist: typing_extensions<5,>=4.3; extra == "dev"
Dynamic: author
Dynamic: author-email
Dynamic: classifier
Dynamic: description
Dynamic: description-content-type
Dynamic: home-page
Dynamic: license
Dynamic: license-file
Dynamic: project-url
Dynamic: provides-extra
Dynamic: requires-dist
Dynamic: requires-python
Dynamic: summary
